veridoc/__init__.py
veridoc/__main__.py
veridoc/cli.py
veridoc/server.py
veridoc/completions/bash_completion.sh
veridoc/completions/fish_completion.fish
veridoc/completions/zsh_completion.zsh
veridoc/core/__init__.py
veridoc/core/config.py
veridoc/core/enhanced_error_handling.py
veridoc/core/file_handler.py
veridoc/core/git_integration.py
veridoc/core/performance_monitor.py
veridoc/core/search_optimization.py
veridoc/core/security.py
veridoc/core/terminal_security.py
veridoc/frontend/index.html
veridoc/frontend/logo.png
veridoc/frontend/css/components.css
veridoc/frontend/css/layout.css
veridoc/frontend/css/main.css
veridoc/frontend/js/app.js
veridoc/frontend/js/components/content-viewer.js
veridoc/frontend/js/components/file-tree.js
veridoc/frontend/js/components/search.js
veridoc/frontend/js/components/terminal.js
veridoc/frontend/js/utils/api.js
veridoc/frontend/js/utils/console-cleaner.js
veridoc/frontend/js/utils/markdown.js
veridoc/frontend/js/utils/url-handler.js
veridoc/models/__init__.py
veridoc/models/api_models.py
veridoc-1.0.2.dist-info/licenses/LICENSE
veridoc-1.0.2.dist-info/METADATA
veridoc-1.0.2.dist-info/WHEEL
veridoc-1.0.2.dist-info/entry_points.txt
veridoc-1.0.2.dist-info/top_level.txt
veridoc-1.0.2.dist-info/RECORD
