Metadata-Version: 2.4
Name: veridoc
Version: 1.0.2
Summary: AI-Optimized Documentation Browser for Rapid Development
Author-email: VeriDoc Team <dev@veridoc.dev>
License: MIT License
Project-URL: Homepage, https://github.com/benny-bc-huang/veridoc
Project-URL: Repository, https://github.com/benny-bc-huang/veridoc
Project-URL: Documentation, https://github.com/benny-bc-huang/veridoc#readme
Project-URL: Bug Tracker, https://github.com/benny-bc-huang/veridoc/issues
Keywords: documentation,browser,ai,development,markdown
Classifier: Development Status :: 5 - Production/Stable
Classifier: Intended Audience :: Developers
Classifier: License :: OSI Approved :: MIT License
Classifier: Operating System :: OS Independent
Classifier: Programming Language :: Python :: 3
Classifier: Programming Language :: Python :: 3.8
Classifier: Programming Language :: Python :: 3.9
Classifier: Programming Language :: Python :: 3.10
Classifier: Programming Language :: Python :: 3.11
Classifier: Topic :: Documentation
Classifier: Topic :: Software Development :: Documentation
Classifier: Topic :: Text Processing :: Markup :: Markdown
Requires-Python: >=3.8
License-File: LICENSE
Requires-Dist: fastapi>=0.104.1
Requires-Dist: uvicorn[standard]>=0.24.0
Requires-Dist: python-multipart>=0.0.6
Requires-Dist: pydantic>=2.5.0
Requires-Dist: aiofiles>=23.2.1
Requires-Dist: watchfiles>=0.21.0
Requires-Dist: python-json-logger>=2.0.7
Requires-Dist: psutil>=5.9.6
Provides-Extra: dev
Requires-Dist: pytest>=7.4.3; extra == "dev"
Requires-Dist: pytest-asyncio>=0.21.1; extra == "dev"
Requires-Dist: httpx>=0.25.2; extra == "dev"
Requires-Dist: black>=23.0.0; extra == "dev"
Requires-Dist: flake8>=6.0.0; extra == "dev"
Requires-Dist: isort>=5.12.0; extra == "dev"
Requires-Dist: mypy>=1.0.0; extra == "dev"
Provides-Extra: test
Requires-Dist: pytest>=7.4.3; extra == "test"
Requires-Dist: pytest-asyncio>=0.21.1; extra == "test"
Requires-Dist: httpx>=0.25.2; extra == "test"
Dynamic: license-file
